smokemsg/__init__.py
smokemsg/linux.py
smokemsg/macos.py
smokemsg/windows.py
smokemsg/zenity.py
SmokeMSG-0.0.1.dev1.dist-info/LICENSE
SmokeMSG-0.0.1.dev1.dist-info/METADATA
SmokeMSG-0.0.1.dev1.dist-info/WHEEL
SmokeMSG-0.0.1.dev1.dist-info/top_level.txt
SmokeMSG-0.0.1.dev1.dist-info/RECORD
