Metadata-Version: 2.1
Name: SmokeMSG
Version: 0.0.1.dev1
Summary: Lightweight Python library to show simple dialogs.
Home-page: https://quantumgui.github.io/smokemsg
Author: Kavindu Santhusa
Author-email: kavindusanthusa@gmail.com
License: UNKNOWN
Project-URL: Bug Reports, https://github.com/quantumgui/smokemsg/issues
Project-URL: Source, https://github.com/quantumgui/smokemsg/
Keywords: dialog,popup,module,pure-python,lightweight,cross-platform,alert,prompt,confirm,question,info,ask
Platform: UNKNOWN
Classifier: Development Status :: 3 - Alpha
Classifier: Intended Audience :: Developers
Classifier: Topic :: Software Development :: Build Tools
Classifier: License :: OSI Approved :: MIT License
Classifier: Operating System :: MacOS :: MacOS X
Classifier: Operating System :: Microsoft :: Windows
Classifier: Operating System :: POSIX
Classifier: Programming Language :: Python :: 2.7
Classifier: Programming Language :: Python
Classifier: Programming Language :: Python :: 3
Classifier: Programming Language :: Python :: 3.5
Classifier: Programming Language :: Python :: 3.6
Classifier: Programming Language :: Python :: 3.7
Classifier: Programming Language :: Python :: 3.8
Classifier: Programming Language :: Python :: 3 :: Only
Classifier: Topic :: Software Development
Classifier: Topic :: Software Development :: User Interfaces
